coloriz.py
coloriz-0.0.1.dist-info/LICENSE
coloriz-0.0.1.dist-info/METADATA
coloriz-0.0.1.dist-info/WHEEL
coloriz-0.0.1.dist-info/top_level.txt
coloriz-0.0.1.dist-info/RECORD
